setup.py
test/__init__.py
test/log_test.py
thinkutils_plus/__init__.py
thinkutils_plus/log.py
thinkutils_plus.egg-info/PKG-INFO
thinkutils_plus.egg-info/SOURCES.txt
thinkutils_plus.egg-info/dependency_links.txt
thinkutils_plus.egg-info/requires.txt
thinkutils_plus.egg-info/top_level.txt
thinkutils_plus/common/BinaryStream.py
thinkutils_plus/common/FileUtils.py
thinkutils_plus/common/PasswordUtils.py
thinkutils_plus/common/PhoneUtils.py
thinkutils_plus/common/ProvinceList.py
thinkutils_plus/common/StringBuilder.py
thinkutils_plus/common/StringUtils.py
thinkutils_plus/common/__init__.py
thinkutils_plus/common/netutils.py
thinkutils_plus/common/object2json.py
thinkutils_plus/common/singleton.py
thinkutils_plus/common/think_hashlib.py
thinkutils_plus/datetime/__init__.py
thinkutils_plus/datetime/datetime.py
thinkutils_plus/encrypt_utils/AES.py
thinkutils_plus/encrypt_utils/RSAEncryption.py
thinkutils_plus/encrypt_utils/__init__.py
thinkutils_plus/eventbus/__init__.py
thinkutils_plus/eventbus/event.py
thinkutils_plus/eventbus/eventbus.py
thinkutils_plus/eventbus/exception.py
thinkutils_plus/eventbus/listener.py
thinkutils_plus/eventbus/taskpool.py
thinkutils_plus/eventbus/util.py
thinkutils_plus/eventbus/sample/__init__.py
thinkutils_plus/eventbus/sample/myevent.py
thinkutils_plus/eventbus/sample/myeventbus.py
thinkutils_plus/eventbus/sample/mylistener.py
thinkutils_plus/redis/RedisLock.py
thinkutils_plus/redis/ThinkRedisPool.py
thinkutils_plus/redis/__init__.py
thinkutils_plus/thread/ThreadPool.py
thinkutils_plus/thread/__init__.py
thinkutils_plus/tornadis/__init__.py
thinkutils_plus/tornadis/benchmark.py
thinkutils_plus/tornadis/client.py
thinkutils_plus/tornadis/connection.py
thinkutils_plus/tornadis/exceptions.py
thinkutils_plus/tornadis/pipeline.py
thinkutils_plus/tornadis/pool.py
thinkutils_plus/tornadis/pubsub.py
thinkutils_plus/tornadis/state.py
thinkutils_plus/tornadis/utils.py
thinkutils_plus/tornadis/write_buffer.py