Metadata-Version: 1.0
Name: thinkutils-plus
Version: 0.0.1
Summary: Thinkman's thinkutils
Home-page: https://github.com/ThinkmanWang/thinkutils_plus
Author: Thinkman
Author-email: wangxf1985@gmail.com
License: MIT Licence
Keywords: pip,thinkman,thinkutils
Platform: any
